launchpad/__init__.py
launchpad/buttons.py
launchpad/colors.py
launchpad/controls.py
python_launchpad-0.2.0.dist-info/METADATA
python_launchpad-0.2.0.dist-info/WHEEL
python_launchpad-0.2.0.dist-info/top_level.txt
python_launchpad-0.2.0.dist-info/RECORD
