Metadata-Version: 2.1
Name: python-launchpad
Version: 0.2.0
Summary: Control a Novation Launchpad with Python
Home-page: https://github.com/BasementCat/launchpad-python
Author: Alec Elton
Author-email: alec.elton@gmail.com
License: UNKNOWN
Platform: UNKNOWN
Classifier: Development Status :: 3 - Alpha
Classifier: Intended Audience :: Developers
Classifier: License :: Other/Proprietary License
Classifier: Natural Language :: English
Classifier: Operating System :: OS Independent
Classifier: Programming Language :: Python :: 3
Requires-Dist: mido
Requires-Dist: python-rtmidi
